jj_pre_push/__init__.py
jj_pre_push/bookmark_updates.py
jj_pre_push/cli.py
jj_pre_push/jj.py
jj_pre_push-0.3.3.dist-info/licenses/LICENSE
jj_pre_push-0.3.3.dist-info/WHEEL
jj_pre_push-0.3.3.dist-info/entry_points.txt
jj_pre_push-0.3.3.dist-info/METADATA
jj_pre_push-0.3.3.dist-info/RECORD
