Metadata-Version: 2.4
Name: jj-pre-push
Version: 0.3.3
Summary: A pre-commit integration for jj
Author: Anthony Carapetis
Author-email: Anthony Carapetis <anthony.carapetis@gmail.com>
License-Expression: Apache-2.0
License-File: LICENSE
Requires-Dist: typer-slim>=0.16.0
Requires-Python: >=3.10
Project-URL: homepage, https://github.com/acarapetis/jj-pre-push
Project-URL: issues, https://github.com/acarapetis/jj-pre-push/issues
Project-URL: source, https://github.com/acarapetis/jj-pre-push
